circle_fit/__init__.py
circle_fit/circle_fit.py
circle_fit-0.2.0.dist-info/METADATA
circle_fit-0.2.0.dist-info/WHEEL
circle_fit-0.2.0.dist-info/licenses/LICENSE
circle_fit-0.2.0.dist-info/RECORD
