Metadata-Version: 2.1
Name: circle-fit
Version: 0.2.0
Summary: A Circle Fitting Library for Python
Project-URL: Homepage, https://github.com/AlliedToasters/circle-fit
Project-URL: Bug Tracker, https://github.com/AlliedToasters/circle-fit/issues
Author-email: Michael Klear <michael.r.klear@gmail.com>, Magne Eik Lauritzen <mag.lauritzen@gmail.com>
License: Copyright (c) 2022 Michael Klear
License-File: LICENSE
Keywords: circle fitting,data science
Classifier: Intended Audience :: Science/Research
Classifier: License :: OSI Approved :: MIT License
Classifier: Operating System :: OS Independent
Classifier: Programming Language :: Python :: 3
Requires-Python: >=3.7
Requires-Dist: matplotlib
Requires-Dist: numpy>=1.21.0
Requires-Dist: scipy
